README.md
setup.py
rmformulas/__init__.py
rmformulas/rmformulas.py
rmformulas.egg-info/PKG-INFO
rmformulas.egg-info/SOURCES.txt
rmformulas.egg-info/dependency_links.txt
rmformulas.egg-info/entry_points.txt
rmformulas.egg-info/requires.txt
rmformulas.egg-info/top_level.txt