Metadata-Version: 2.1
Name: rmformulas
Version: 1.0.0
Summary: Remove formulas CLI
Home-page: https://github.com/team-care/remove-formulas-CLI
Author: HigashidaTomoyuki
License: MIT
Platform: UNKNOWN
